{
    "edges": [
        [
            "Conv2D",
            "CustomCropLayer"
        ],
        [
            "CustomCropLayer",
            "MaxPooling2D"
        ],
        [
            "MaxPooling2D",
            "CustomPadLayer"
        ],
        [
            "CustomPadLayer",
            "BatchNormalization"
        ],
        [
            "BatchNormalization",
            "Conv2D"
        ],
        [
            "Conv2D",
            "MaxPooling2D"
        ],
        [
            "MaxPooling2D",
            "BatchNormalization"
        ],
        [
            "MaxPooling2D",
            "MaxPooling2D"
        ],
        [
            "BatchNormalization",
            "CustomPadLayer"
        ],
        [
            "CustomPadLayer",
            "CustomCropLayer"
        ],
        [
            "CustomCropLayer",
            "Conv2D"
        ],
        [
            "Conv2D",
            "Conv2D"
        ],
        [
            "Conv2D",
            "Dropout"
        ],
        [
            "MaxPooling2D",
            "CustomExpandLayer"
        ],
        [
            "CustomExpandLayer",
            "BatchNormalization"
        ],
        [
            "BatchNormalization",
            "CustomDropDimLayer"
        ],
        [
            "CustomDropDimLayer",
            "CustomDropDimLayer"
        ],
        [
            "CustomDropDimLayer",
            "Dropout"
        ],
        [
            "CustomDropDimLayer",
            "CustomPadLayer"
        ],
        [
            "CustomCropLayer",
            "Flatten"
        ],
        [
            "Flatten",
            "CustomPadLayer"
        ],
        [
            "CustomPadLayer",
            "Dense"
        ],
        [
            "CustomPadLayer",
            "Dropout"
        ],
        [
            "Dense",
            "Dropout"
        ],
        [
            "Dropout",
            "Dense"
        ],
        [
            "MaxPooling2D",
            "Flatten"
        ],
        [
            "Dropout",
            "Flatten"
        ],
        [
            "Dropout",
            "Dropout"
        ],
        [
            "Dense",
            "Dense"
        ],
        [
            "Flatten",
            "Dense"
        ],
        [
            "Dense",
            "Add"
        ]
    ],
    "layer_config": {
        "Conv2D": [
            {
                "trainable": true,
                "batch_input_shape": [
                    null,
                    32,
                    32,
                    3
                ],
                "dtype": "float32",
                "kernel_size": [
                    3,
                    3
                ],
                "strides": [
                    2,
                    2
                ],
                "padding": "same",
                "data_format": "channels_last",
                "dilation_rate": [
                    1,
                    1
                ],
                "groups": 1,
                "activation": "relu",
                "use_bias": true,
                "kernel_initializer": {
                    "class_name": "VarianceScaling",
                    "config": {
                        "scale": 1.0,
                        "mode": "fan_avg",
                        "distribution": "uniform",
                        "seed": null
                    }
                },
                "bias_initializer": {
                    "class_name": "Zeros",
                    "config": {}
                },
                "kernel_regularizer": null,
                "bias_regularizer": null,
                "activity_regularizer": null,
                "kernel_constraint": null,
                "bias_constraint": null
            },
            {
                "trainable": true,
                "dtype": "float32",
                "kernel_size": [
                    5,
                    5
                ],
                "strides": [
                    1,
                    1
                ],
                "padding": "same",
                "data_format": "channels_last",
                "dilation_rate": [
                    1,
                    1
                ],
                "groups": 1,
                "activation": "relu",
                "use_bias": true,
                "kernel_initializer": {
                    "class_name": "VarianceScaling",
                    "config": {
                        "scale": 1.0,
                        "mode": "fan_avg",
                        "distribution": "uniform",
                        "seed": null
                    }
                },
                "bias_initializer": {
                    "class_name": "Zeros",
                    "config": {}
                },
                "kernel_regularizer": null,
                "bias_regularizer": null,
                "activity_regularizer": null,
                "kernel_constraint": null,
                "bias_constraint": null
            },
            {
                "trainable": true,
                "dtype": "float32",
                "kernel_size": [
                    3,
                    3
                ],
                "strides": [
                    1,
                    1
                ],
                "padding": "same",
                "data_format": "channels_last",
                "dilation_rate": [
                    1,
                    1
                ],
                "groups": 1,
                "activation": "relu",
                "use_bias": true,
                "kernel_initializer": {
                    "class_name": "VarianceScaling",
                    "config": {
                        "scale": 1.0,
                        "mode": "fan_avg",
                        "distribution": "uniform",
                        "seed": null
                    }
                },
                "bias_initializer": {
                    "class_name": "Zeros",
                    "config": {}
                },
                "kernel_regularizer": null,
                "bias_regularizer": null,
                "activity_regularizer": null,
                "kernel_constraint": null,
                "bias_constraint": null
            }
        ],
        "CustomCropLayer": [
            {
                "trainable": true,
                "dtype": "float32",
                "cropping": [
                    [
                        4,
                        5
                    ],
                    [
                        6,
                        7
                    ],
                    [
                        44,
                        45
                    ]
                ]
            },
            {
                "trainable": true,
                "dtype": "float32",
                "cropping": [
                    [
                        0,
                        0
                    ],
                    [
                        0,
                        0
                    ],
                    [
                        124,
                        124
                    ]
                ]
            },
            {
                "trainable": true,
                "dtype": "float32",
                "cropping": [
                    [
                        3,
                        3
                    ],
                    [
                        1,
                        1
                    ],
                    [
                        0,
                        0
                    ]
                ]
            },
            {
                "trainable": true,
                "dtype": "float32",
                "cropping": [
                    [
                        0,
                        0
                    ],
                    [
                        124,
                        124
                    ]
                ]
            }
        ],
        "MaxPooling2D": [
            {
                "trainable": true,
                "dtype": "float32",
                "pool_size": [
                    2,
                    2
                ],
                "padding": "valid",
                "strides": [
                    2,
                    2
                ],
                "data_format": "channels_last"
            },
            {
                "trainable": true,
                "dtype": "float32",
                "pool_size": [
                    3,
                    3
                ],
                "padding": "valid",
                "strides": [
                    2,
                    2
                ],
                "data_format": "channels_last"
            }
        ],
        "CustomPadLayer": [
            {
                "trainable": true,
                "dtype": "float32",
                "padding": [
                    [
                        2,
                        3
                    ],
                    [
                        3,
                        4
                    ],
                    [
                        44,
                        45
                    ]
                ],
                "constant_values": 2
            },
            {
                "trainable": true,
                "dtype": "float32",
                "padding": [
                    [
                        3,
                        3
                    ],
                    [
                        1,
                        1
                    ],
                    [
                        0,
                        0
                    ]
                ],
                "constant_values": 2
            },
            {
                "trainable": true,
                "dtype": "float32",
                "padding": [
                    [
                        4,
                        4
                    ],
                    [
                        0,
                        0
                    ]
                ],
                "constant_values": 2
            },
            {
                "trainable": true,
                "dtype": "float32",
                "padding": [
                    [
                        92,
                        92
                    ]
                ],
                "constant_values": 2
            }
        ],
        "BatchNormalization": [
            {
                "trainable": true,
                "dtype": "float32",
                "axis": [
                    3
                ],
                "momentum": 0.99,
                "epsilon": 0.001,
                "center": true,
                "scale": true,
                "beta_initializer": {
                    "class_name": "Zeros",
                    "config": {}
                },
                "gamma_initializer": {
                    "class_name": "Ones",
                    "config": {}
                },
                "moving_mean_initializer": {
                    "class_name": "Zeros",
                    "config": {}
                },
                "moving_variance_initializer": {
                    "class_name": "Ones",
                    "config": {}
                },
                "beta_regularizer": null,
                "gamma_regularizer": null,
                "beta_constraint": null,
                "gamma_constraint": null
            }
        ],
        "CustomExpandLayer": [
            {
                "trainable": true,
                "dtype": "float32",
                "axis": 1
            }
        ],
        "CustomDropDimLayer": [
            {
                "trainable": true,
                "dtype": "float32",
                "axis": 1
            }
        ],
        "Flatten": [
            {
                "trainable": true,
                "dtype": "float32",
                "data_format": "channels_last"
            }
        ],
        "Dense": [
            {
                "trainable": true,
                "dtype": "float32",
                "activation": "relu",
                "use_bias": true,
                "kernel_initializer": {
                    "class_name": "VarianceScaling",
                    "config": {
                        "scale": 1.0,
                        "mode": "fan_avg",
                        "distribution": "uniform",
                        "seed": null
                    }
                },
                "bias_initializer": {
                    "class_name": "Zeros",
                    "config": {}
                },
                "kernel_regularizer": null,
                "bias_regularizer": null,
                "activity_regularizer": null,
                "kernel_constraint": null,
                "bias_constraint": null
            },
            {
                "trainable": true,
                "dtype": "float32",
                "activation": "softmax",
                "use_bias": true,
                "kernel_initializer": {
                    "class_name": "VarianceScaling",
                    "config": {
                        "scale": 1.0,
                        "mode": "fan_avg",
                        "distribution": "uniform",
                        "seed": null
                    }
                },
                "bias_initializer": {
                    "class_name": "Zeros",
                    "config": {}
                },
                "kernel_regularizer": null,
                "bias_regularizer": null,
                "activity_regularizer": null,
                "kernel_constraint": null,
                "bias_constraint": null
            },
            {
                "trainable": true,
                "dtype": "float32",
                "activation": "linear",
                "use_bias": true,
                "kernel_initializer": {
                    "class_name": "GlorotUniform",
                    "config": {
                        "seed": null
                    }
                },
                "bias_initializer": {
                    "class_name": "Zeros",
                    "config": {}
                },
                "kernel_regularizer": null,
                "bias_regularizer": null,
                "activity_regularizer": null,
                "kernel_constraint": null,
                "bias_constraint": null
            }
        ],
        "Dropout": [
            {
                "trainable": true,
                "dtype": "float32",
                "rate": 0.5,
                "noise_shape": null,
                "seed": null
            }
        ],
        "Add": [
            {
                "trainable": true,
                "dtype": "float32"
            }
        ]
    },
    "layer_input_info": {
        "Conv2D": {
            "input_dims": [
                4
            ],
            "dtype": [
                "<dtype: 'float32'>"
            ],
            "shape": [
                "[None, 32, 32, 3]",
                "[None, 8, 8, 96]",
                "[None, 9, 5, 8]",
                "[None, 3, 3, 384]"
            ]
        },
        "CustomCropLayer": {
            "input_dims": [
                4,
                3
            ],
            "dtype": [
                "<dtype: 'float32'>"
            ],
            "shape": [
                "[None, 16, 16, 96]",
                "[None, 9, 5, 256]",
                "[None, 9, 5, 384]",
                "[None, 9, 256]"
            ]
        },
        "MaxPooling2D": {
            "input_dims": [
                4
            ],
            "dtype": [
                "<dtype: 'float32'>"
            ],
            "shape": [
                "[None, 7, 3, 7]",
                "[None, 8, 8, 256]",
                "[None, 3, 3, 256]"
            ]
        },
        "CustomPadLayer": {
            "input_dims": [
                4,
                3,
                2
            ],
            "dtype": [
                "<dtype: 'float32'>"
            ],
            "shape": [
                "[None, 3, 1, 7]",
                "[None, 3, 3, 256]",
                "[None, 1, 256]",
                "[None, 72]"
            ]
        },
        "BatchNormalization": {
            "input_dims": [
                4,
                5
            ],
            "dtype": [
                "<dtype: 'float32'>"
            ],
            "shape": [
                "[None, 8, 8, 96]",
                "[None, 3, 3, 256]",
                "[None, 1, 1, 1, 256]"
            ]
        },
        "CustomExpandLayer": {
            "input_dims": [
                4
            ],
            "dtype": [
                "<dtype: 'float32'>"
            ],
            "shape": [
                "[None, 1, 1, 256]"
            ]
        },
        "CustomDropDimLayer": {
            "input_dims": [
                5,
                4
            ],
            "dtype": [
                "<dtype: 'float32'>"
            ],
            "shape": [
                "[None, 1, 1, 1, 256]",
                "[None, 1, 1, 256]"
            ]
        },
        "Flatten": {
            "input_dims": [
                3,
                4
            ],
            "dtype": [
                "<dtype: 'float32'>"
            ],
            "shape": [
                "[None, 9, 8]",
                "[None, 1, 1, 256]",
                "[None, 3, 3, 256]"
            ]
        },
        "Dense": {
            "input_dims": [
                2
            ],
            "dtype": [
                "<dtype: 'float32'>"
            ],
            "shape": [
                "[None, 256]",
                "[None, 4096]",
                "[None, 10]",
                "[None, 2304]"
            ]
        },
        "Dropout": {
            "input_dims": [
                2,
                4
            ],
            "dtype": [
                "<dtype: 'float32'>"
            ],
            "shape": [
                "[None, 4096]",
                "[None, 1, 1, 256]",
                "[None, 256]",
                "[None, 3, 3, 256]"
            ]
        },
        "Add": {
            "input_dims": [
                2
            ],
            "dtype": [
                "<dtype: 'float32'>"
            ],
            "shape": [
                "[None, 100]"
            ]
        }
    },
    "layer_num": 42,
    "layer_type": [
        "Conv2D",
        "CustomCropLayer",
        "MaxPooling2D",
        "CustomPadLayer",
        "BatchNormalization",
        "CustomExpandLayer",
        "CustomDropDimLayer",
        "Flatten",
        "Dense",
        "Dropout",
        "Add"
    ],
    "cur_edge_num": 42,
    "layer_dims": {
        "Conv2D": {
            "input_dims": [
                4
            ],
            "output_dims": [
                4
            ]
        },
        "CustomCropLayer": {
            "input_dims": [
                4,
                3
            ],
            "output_dims": [
                4,
                3
            ]
        },
        "MaxPooling2D": {
            "input_dims": [
                4
            ],
            "output_dims": [
                4
            ]
        },
        "CustomPadLayer": {
            "input_dims": [
                4,
                3,
                2
            ],
            "output_dims": [
                4,
                3,
                2
            ]
        },
        "BatchNormalization": {
            "input_dims": [
                4,
                5
            ],
            "output_dims": [
                4,
                5
            ]
        },
        "CustomExpandLayer": {
            "input_dims": [
                4
            ],
            "output_dims": [
                5
            ]
        },
        "CustomDropDimLayer": {
            "input_dims": [
                5,
                4
            ],
            "output_dims": [
                4,
                3
            ]
        },
        "Flatten": {
            "input_dims": [
                3,
                4
            ],
            "output_dims": [
                2
            ]
        },
        "Dense": {
            "input_dims": [
                2
            ],
            "output_dims": [
                2
            ]
        },
        "Dropout": {
            "input_dims": [
                2,
                4
            ],
            "output_dims": [
                2,
                4
            ]
        },
        "Add": {
            "input_dims": [
                2
            ],
            "output_dims": [
                2
            ]
        }
    }
}